jetstream_config_parser/__init__.py
jetstream_config_parser/alert.py
jetstream_config_parser/analysis.py
jetstream_config_parser/config.py
jetstream_config_parser/data_source.py
jetstream_config_parser/definition.py
jetstream_config_parser/dimension.py
jetstream_config_parser/errors.py
jetstream_config_parser/experiment.py
jetstream_config_parser/exposure_signal.py
jetstream_config_parser/function.py
jetstream_config_parser/metric.py
jetstream_config_parser/monitoring.py
jetstream_config_parser/outcome.py
jetstream_config_parser/parameter.py
jetstream_config_parser/population.py
jetstream_config_parser/pre_treatment.py
jetstream_config_parser/project.py
jetstream_config_parser/segment.py
jetstream_config_parser/statistic.py
jetstream_config_parser/util.py
jetstream_config_parser/tests/__init__.py
jetstream_config_parser/tests/conftest.py
jetstream_config_parser/tests/test_alert.py
jetstream_config_parser/tests/test_analysis.py
jetstream_config_parser/tests/test_config.py
jetstream_config_parser/tests/test_experiment.py
jetstream_config_parser/tests/test_function.py
jetstream_config_parser/tests/test_metric.py
jetstream_config_parser/tests/test_monitoring.py
jetstream_config_parser/tests/test_outcomes.py
jetstream_config_parser/tests/test_parameter.py
jetstream_config_parser/tests/test_population.py
jetstream_config_parser/tests/test_project.py
jetstream_config_parser/tests/data/default_metrics.toml
jetstream_config_parser/tests/integration/test_config_integration.py
mozilla_jetstream_config_parser-2022.10.6.dist-info/LICENSE
mozilla_jetstream_config_parser-2022.10.6.dist-info/METADATA
mozilla_jetstream_config_parser-2022.10.6.dist-info/WHEEL
mozilla_jetstream_config_parser-2022.10.6.dist-info/top_level.txt
mozilla_jetstream_config_parser-2022.10.6.dist-info/RECORD
